setup.py
django_pulseware.egg-info/PKG-INFO
django_pulseware.egg-info/SOURCES.txt
django_pulseware.egg-info/dependency_links.txt
django_pulseware.egg-info/top_level.txt
pulseware/__init__.py
pulseware/admin.py
pulseware/apps.py
pulseware/defaults.py
pulseware/models.py
pulseware/receivers.py
pulseware/__pycache__/__init__.cpython-34.pyc
pulseware/__pycache__/admin.cpython-34.pyc
pulseware/__pycache__/apps.cpython-34.pyc
pulseware/__pycache__/models.cpython-34.pyc
pulseware/__pycache__/receivers.cpython-34.pyc
pulseware/middleware/__init__.py
pulseware/middleware/heartbeat.py
pulseware/migrations/0001_initial.py
pulseware/migrations/__init__.py
pulseware/migrations/__pycache__/0001_initial.cpython-34.pyc
pulseware/migrations/__pycache__/__init__.cpython-34.pyc
pulseware/tests/__init__.py
pulseware/tests/tests.py
pulseware/tests/testsettings.py