Metadata-Version: 1.1
Name: django-pulseware
Version: 0.0.2
Summary: A Django health check application
Home-page: https://github.com/un33k/django-pulseware
Author: Val Neekman
Author-email: info@neekware.com
License: BSD
Platform: UNKNOWN
Classifier: Development Status :: 3 - Alpha
Classifier: Environment :: Web Environment
Classifier: Intended Audience :: Developers
Classifier: License :: OSI Approved :: BSD License
Classifier: Operating System :: OS Independent
Classifier: Programming Language :: Python
Classifier: Topic :: Utilities
